git_hooks_1c-9.10.8.dist-info/METADATA
git_hooks_1c-9.10.8.dist-info/WHEEL
git_hooks_1c-9.10.8.dist-info/entry_points.txt
git_hooks_1c/__about__.py
git_hooks_1c/__init__.py
git_hooks_1c/__main__.py
git_hooks_1c/cli.py
git_hooks_1c/core.py
git_hooks_1c/install.py
git_hooks_1c/pre_commit.py
git_hooks_1c/uninstall.py
tests/__init__.py
tests/test_pre_commit.py
git_hooks_1c-9.10.8.dist-info/RECORD
