Metadata-Version: 2.1
Name: git-hooks-1c
Version: 9.10.8
Summary: Git hooks utilities for 1C:Enterprise
Keywords: 1c,git,pre-commit,v8reader,v8unpack,gcomp
Author-Email: Cujoko <cujoko@gmail.com>
License: MIT
Classifier: Development Status :: 5 - Production/Stable
Classifier: Intended Audience :: Developers
Classifier: License :: OSI Approved :: MIT License
Classifier: Natural Language :: Russian
Classifier: Programming Language :: Python :: 3.14
Classifier: Programming Language :: Python :: 3.13
Classifier: Programming Language :: Python :: 3.12
Classifier: Programming Language :: Python :: 3.11
Classifier: Programming Language :: Python :: 3.10
Classifier: Topic :: Software Development
Classifier: Topic :: Utilities
Project-URL: repository, https://github.com/Cujoko-Dev/git-hooks-1c
Requires-Python: >=3.10
Requires-Dist: cjk-commons<4.0.0,>=3.6.3
Requires-Dist: fleep>=1.0.1
Requires-Dist: loguru>=0.6.0
Requires-Dist: parse-1c-build<6.0.0,>=5.15.2
Requires-Dist: plumbum>=1.8.1
